<TextureAtlas imagePath="sheet.png">
	<SubTexture name="blink_00000.tga" x="0" y="426" width="186" height="140"/>
	<SubTexture name="blink_00001.tga" x="0" y="426" width="186" height="140"/>
	<SubTexture name="blink_00002.tga" x="0" y="852" width="186" height="140"/>
	<SubTexture name="blink_00003.tga" x="0" y="852" width="186" height="140"/>
	<SubTexture name="blink_00004.tga" x="0" y="852" width="186" height="140"/>
	<SubTexture name="blink_00005.tga" x="0" y="852" width="186" height="140"/>
	<SubTexture name="blink_00006.tga" x="0" y="852" width="186" height="140"/>
	<SubTexture name="blink_00007.tga" x="0" y="568" width="186" height="140"/>
	<SubTexture name="blink_00008.tga" x="0" y="426" width="186" height="140"/>
	<SubTexture name="blink_00009.tga" x="0" y="426" width="186" height="140"/>
	<SubTexture name="broute_00000.tga" x="0" y="426" width="186" height="140"/>
	<SubTexture name="broute_00001.tga" x="0" y="426" width="186" height="140"/>
	<SubTexture name="broute_00002.tga" x="0" y="426" width="186" height="140"/>
	<SubTexture name="broute_00003.tga" x="0" y="426" width="186" height="140"/>
	<SubTexture name="broute_00004.tga" x="0" y="710" width="186" height="140"/>
	<SubTexture name="broute_00005.tga" x="0" y="710" width="186" height="140"/>
	<SubTexture name="broute_00006.tga" x="0" y="710" width="186" height="140"/>
	<SubTexture name="broute_00007.tga" x="0" y="710" width="186" height="140"/>
	<SubTexture name="broute_00008.tga" x="0" y="710" width="186" height="140"/>
	<SubTexture name="broute_00009.tga" x="0" y="710" width="186" height="140"/>
	<SubTexture name="broute_00010.tga" x="0" y="0" width="188" height="140"/>
	<SubTexture name="broute_00011.tga" x="0" y="0" width="188" height="140"/>
	<SubTexture name="broute_00012.tga" x="0" y="0" width="188" height="140"/>
	<SubTexture name="broute_00013.tga" x="0" y="0" width="188" height="140"/>
	<SubTexture name="broute_00014.tga" x="0" y="142" width="186" height="140"/>
	<SubTexture name="broute_00015.tga" x="0" y="142" width="186" height="140"/>
	<SubTexture name="broute_00016.tga" x="0" y="284" width="186" height="140"/>
	<SubTexture name="broute_00017.tga" x="0" y="284" width="186" height="140"/>
	<SubTexture name="broute_00018.tga" x="0" y="142" width="186" height="140"/>
	<SubTexture name="broute_00019.tga" x="0" y="142" width="186" height="140"/>
	<SubTexture name="broute_00020.tga" x="0" y="284" width="186" height="140"/>
	<SubTexture name="broute_00021.tga" x="0" y="284" width="186" height="140"/>
	<SubTexture name="broute_00022.tga" x="0" y="142" width="186" height="140"/>
	<SubTexture name="broute_00023.tga" x="0" y="142" width="186" height="140"/>
	<SubTexture name="broute_00024.tga" x="0" y="284" width="186" height="140"/>
	<SubTexture name="broute_00025.tga" x="0" y="284" width="186" height="140"/>
	<SubTexture name="broute_00026.tga" x="0" y="426" width="186" height="140"/>
	<SubTexture name="broute_00027.tga" x="0" y="426" width="186" height="140"/>
	<SubTexture name="broute_00028.tga" x="0" y="426" width="186" height="140"/>
	<SubTexture name="broute_00029.tga" x="0" y="426" width="186" height="140"/>
	<SubTexture name="boule_00000.tga" x="188" y="845" width="175" height="140"/>
	<SubTexture name="boule_00001.tga" x="534" y="653" width="139" height="139"/>
	<SubTexture name="boule_00002.tga" x="533" y="509" width="139" height="142"/>
	<SubTexture name="boule_00003.tga" x="517" y="185" width="139" height="145"/>
	<SubTexture name="boule_00004.tga" x="517" y="61" width="139" height="122"/>
	<SubTexture name="boule_00005.tga" x="372" y="425" width="140" height="105"/>
	<SubTexture name="boule_00006.tga" x="375" y="61" width="140" height="113"/>
	<SubTexture name="boule_00007.tga" x="373" y="284" width="140" height="82"/>
	<SubTexture name="boule_00008.tga" x="375" y="176" width="140" height="105"/>
	<SubTexture name="boule_00009.tga" x="507" y="849" width="140" height="108"/>
	<SubTexture name="boule_00010.tga" x="365" y="849" width="140" height="112"/>
	<SubTexture name="boule_00011.tga" x="362" y="0" width="167" height="59"/>
	<SubTexture name="boule_00012.tga" x="658" y="118" width="132" height="118"/>
	<SubTexture name="boule_00013.tga" x="675" y="672" width="132" height="105"/>
	<SubTexture name="boule_00014.tga" x="675" y="672" width="132" height="105"/>
	<SubTexture name="retournormal_00000.tga" x="675" y="565" width="132" height="105"/>
	<SubTexture name="retournormal_00001.tga" x="674" y="458" width="132" height="105"/>
	<SubTexture name="retournormal_00002.tga" x="658" y="0" width="134" height="116"/>
	<SubTexture name="retournormal_00003.tga" x="656" y="332" width="136" height="124"/>
	<SubTexture name="retournormal_00004.tga" x="649" y="794" width="138" height="131"/>
	<SubTexture name="retournormal_00005.tga" x="514" y="368" width="140" height="139"/>
	<SubTexture name="retournormal_00006.tga" x="188" y="845" width="175" height="140"/>
	<SubTexture name="retournormal_00007.tga" x="188" y="845" width="175" height="140"/>
	<SubTexture name="retournormal_00008.tga" x="365" y="707" width="167" height="140"/>
	<SubTexture name="retournormal_00009.tga" x="188" y="142" width="185" height="140"/>
	<SubTexture name="retournormal_00010.tga" x="188" y="425" width="182" height="138"/>
	<SubTexture name="retournormal_00011.tga" x="188" y="565" width="178" height="140"/>
	<SubTexture name="retournormal_00012.tga" x="188" y="284" width="183" height="139"/>
	<SubTexture name="retournormal_00013.tga" x="0" y="426" width="186" height="140"/>
	<SubTexture name="retournormal_00014.tga" x="0" y="426" width="186" height="140"/>
	<SubTexture name="tortue_00000.tga" x="0" y="426" width="186" height="140"/>
	<SubTexture name="tortue_00001.tga" x="0" y="426" width="186" height="140"/>
	<SubTexture name="tortue_00002.tga" x="188" y="284" width="183" height="139"/>
	<SubTexture name="tortue_00003.tga" x="188" y="565" width="178" height="140"/>
	<SubTexture name="tortue_00004.tga" x="188" y="425" width="182" height="138"/>
	<SubTexture name="tortue_00005.tga" x="188" y="142" width="185" height="140"/>
	<SubTexture name="tortue_00006.tga" x="365" y="707" width="167" height="140"/>
	<SubTexture name="tortue_00007.tga" x="190" y="0" width="170" height="138"/>
	<SubTexture name="tortue_00008.tga" x="190" y="0" width="170" height="138"/>
	<SubTexture name="tortue_00009.tga" x="368" y="565" width="163" height="140"/>
	<SubTexture name="tortue_00010.tga" x="188" y="707" width="175" height="136"/>
	<SubTexture name="tortue_00011.tga" x="188" y="845" width="175" height="140"/>
	<SubTexture name="tortue_00012.tga" x="368" y="565" width="163" height="140"/>
	<SubTexture name="tortue_00013.tga" x="188" y="845" width="175" height="140"/>
	<SubTexture name="tortue_00014.tga" x="188" y="845" width="175" height="140"/>
</TextureAtlas>